src/__init__.py
src/cli/__init__.py
src/cli/cli.py
src/cli/state.py
src/cli/utilities.py
src/common/__init__.py
src/common/base_logger.py
src/common/config.py
src/common/exceptions.py
src/enums/__init__.py
src/enums/common.py
src/enums/datasets.py
src/enums/secrets.py
src/enums/sources.py
src/enums/targets.py
src/governance/__init__.py
src/governance/audit/__init__.py
src/governance/cli.py
src/governance/lineage/__init__.py
src/governance/notification/__init__.py
src/governance/notification/atlassian.py
src/governance/notification/email.py
src/governance/notification/incident_io.py
src/governance/notification/pager_duty.py
src/governance/notification/slack.py
src/governance/notification/teams.py
src/governance/notification/xmatters.py
src/kubernetes/__init__.py
src/kubernetes/pod_utils.py
src/metadata/__init__.py
src/models/__init__.py
src/models/common.py
src/models/dataset/__init__.py
src/models/dataset/api.py
src/models/dataset/base.py
src/models/dataset/file.py
src/models/dataset/stream.py
src/models/dataset/table.py
src/models/pipeline.py
src/models/secrets.py
src/models/source.py
src/models/target.py
src/models/transform.py
src/models/validation.py
src/sources/__init__.py
src/sources/api/__init__.py
src/sources/api/github/__init__.py
src/sources/api/jira/__init__.py
src/sources/aws/__init__.py
src/sources/aws/aws_athena/__init__.py
src/sources/aws/aws_kinesis/__init__.py
src/sources/aws/aws_s3/__init__.py
src/sources/aws/aws_sqs/__init__.py
src/sources/aws/dynamodb/__init__.py
src/sources/aws/redshift/__init__.py
src/sources/azure/__init__.py
src/sources/azure/azure_blob_storage/__init__.py
src/sources/base.py
src/sources/database/__init__.py
src/sources/database/base.py
src/sources/database/databricks/__init__.py
src/sources/database/db2/__init__.py
src/sources/database/duckdb/__init__.py
src/sources/database/elasticsearch/__init__.py
src/sources/database/iceberg/__init__.py
src/sources/database/mongodb/__init__.py
src/sources/database/mysql/__init__.py
porter_py-0.0.2rc2.dist-info/METADATA
porter_py-0.0.2rc2.dist-info/WHEEL
porter_py-0.0.2rc2.dist-info/entry_points.txt
porter_py-0.0.2rc2.dist-info/licenses/LICENSE
porter_py-0.0.2rc2.dist-info/RECORD
